smbio/__init__.py
smbio/agnostic_path.py
smbio/connector.py
smbio/file_entry.py
smbio/io.py
smbio-0.1.0.dist-info/LICENSE
smbio-0.1.0.dist-info/METADATA
smbio-0.1.0.dist-info/WHEEL
smbio-0.1.0.dist-info/RECORD
