Metadata-Version: 2.1
Name: smbio
Version: 0.1.0
Summary: SMB protocol wrapper for python
License: MIT
Author: German Arutyunov
Author-email: germanarutyunov@gmail.com
Requires-Python: >=3.10,<4.0
Classifier: License :: OSI Approved :: MIT License
Classifier: Programming Language :: Python :: 3
Classifier: Programming Language :: Python :: 3.10
Classifier: Programming Language :: Python :: 3.11
Classifier: Programming Language :: Python :: 3.12
Requires-Dist: smbprotocol (>=1.12.0,<2.0.0)
